Metadata-Version: 2.1
Name: simple-sqlite-helper
Version: 1.0.0
Summary: Python module for easy sqlite database management
Home-page: https://api.logicarbor.com/sqlitehelper/documentation.html
Author: samet-catakli
Author-email: samet@logicarbor.com
Classifier: Development Status :: 3 - Alpha
Classifier: Intended Audience :: Developers
Classifier: License :: OSI Approved :: MIT License
Classifier: Programming Language :: Python :: 3.7
Classifier: Programming Language :: Python :: 3.8
Classifier: Programming Language :: Python :: 3.9
